{
    "id": "186",
    "condition": "2",
    "results": {
        "id": "186",
        "condition": "2",
        "results": {
            "trainingPhase": [
                [
                    "trial",
                    "block",
                    "s1",
                    "s2",
                    "connected",
                    "response",
                    "accuracy",
                    "rt"
                ],
                [
                    0,
                    0,
                    "./static/experiments/de2/materials/stim_files/15.png",
                    "./static/experiments/de2/materials/stim_files/7.png",
                    null,
                    null,
                    null,
                    6
                ],
                [
                    1,
                    0,
                    "./static/experiments/de2/materials/stim_files/13.png",
                    "./static/experiments/de2/materials/stim_files/5.png",
                    null,
                    null,
                    null,
                    12270
                ],
                [
                    2,
                    0,
                    "./static/experiments/de2/materials/stim_files/4.png",
                    "./static/experiments/de2/materials/stim_files/12.png",
                    null,
                    null,
                    null,
                    10037
                ],
                [
                    3,
                    0,
                    "./static/experiments/de2/materials/stim_files/6.png",
                    "./static/experiments/de2/materials/stim_files/14.png",
                    null,
                    null,
                    null,
                    6585
                ],
                [
                    4,
                    0,
                    "./static/experiments/de2/materials/stim_files/3.png",
                    "./static/experiments/de2/materials/stim_files/11.png",
                    null,
                    null,
                    null,
                    8136
                ],
                [
                    5,
                    0,
                    "./static/experiments/de2/materials/stim_files/1.png",
                    "./static/experiments/de2/materials/stim_files/9.png",
                    null,
                    null,
                    null,
                    11727
                ],
                [
                    6,
                    0,
                    "./static/experiments/de2/materials/stim_files/6.png",
                    "./static/experiments/de2/materials/stim_files/14.png",
                    null,
                    null,
                    null,
                    4157
                ],
                [
                    7,
                    0,
                    "./static/experiments/de2/materials/stim_files/16.png",
                    "./static/experiments/de2/materials/stim_files/8.png",
                    null,
                    null,
                    null,
                    4845
                ],
                [
                    8,
                    0,
                    "./static/experiments/de2/materials/stim_files/9.png",
                    "./static/experiments/de2/materials/stim_files/1.png",
                    null,
                    null,
                    null,
                    15016
                ],
                [
                    9,
                    0,
                    "./static/experiments/de2/materials/stim_files/11.png",
                    "./static/experiments/de2/materials/stim_files/3.png",
                    null,
                    null,
                    null,
                    5339
                ],
                [
                    10,
                    0,
                    "./static/experiments/de2/materials/stim_files/13.png",
                    "./static/experiments/de2/materials/stim_files/5.png",
                    null,
                    null,
                    null,
                    5585
                ],
                [
                    11,
                    0,
                    "./static/experiments/de2/materials/stim_files/8.png",
                    "./static/experiments/de2/materials/stim_files/16.png",
                    null,
                    null,
                    null,
                    8922
                ],
                [
                    12,
                    0,
                    "./static/experiments/de2/materials/stim_files/2.png",
                    "./static/experiments/de2/materials/stim_files/10.png",
                    null,
                    null,
                    null,
                    3700
                ],
                [
                    13,
                    0,
                    "./static/experiments/de2/materials/stim_files/2.png",
                    "./static/experiments/de2/materials/stim_files/10.png",
                    null,
                    null,
                    null,
                    7223
                ],
                [
                    14,
                    0,
                    "./static/experiments/de2/materials/stim_files/4.png",
                    "./static/experiments/de2/materials/stim_files/12.png",
                    null,
                    null,
                    null,
                    4410
                ],
                [
                    15,
                    0,
                    "./static/experiments/de2/materials/stim_files/7.png",
                    "./static/experiments/de2/materials/stim_files/15.png",
                    null,
                    null,
                    null,
                    37865
                ],
                [
                    0,
                    1,
                    "./static/experiments/de2/materials/stim_files/3.png",
                    "./static/experiments/de2/materials/stim_files/11.png",
                    null,
                    null,
                    null,
                    5420
                ],
                [
                    1,
                    1,
                    "./static/experiments/de2/materials/stim_files/2.png",
                    "./static/experiments/de2/materials/stim_files/10.png",
                    null,
                    null,
                    null,
                    4036
                ],
                [
                    2,
                    1,
                    "./static/experiments/de2/materials/stim_files/7.png",
                    "./static/experiments/de2/materials/stim_files/15.png",
                    null,
                    null,
                    null,
                    5555
                ],
                [
                    3,
                    1,
                    "./static/experiments/de2/materials/stim_files/5.png",
                    "./static/experiments/de2/materials/stim_files/13.png",
                    null,
                    null,
                    null,
                    9090
                ],
                [
                    4,
                    1,
                    "./static/experiments/de2/materials/stim_files/4.png",
                    "./static/experiments/de2/materials/stim_files/12.png",
                    null,
                    null,
                    null,
                    17569
                ],
                [
                    5,
                    1,
                    "./static/experiments/de2/materials/stim_files/2.png",
                    "./static/experiments/de2/materials/stim_files/10.png",
                    null,
                    null,
                    null,
                    5796
                ],
                [
                    6,
                    1,
                    "./static/experiments/de2/materials/stim_files/1.png",
                    "./static/experiments/de2/materials/stim_files/9.png",
                    null,
                    null,
                    null,
                    5145
                ],
                [
                    7,
                    1,
                    "./static/experiments/de2/materials/stim_files/3.png",
                    "./static/experiments/de2/materials/stim_files/11.png",
                    null,
                    null,
                    null,
                    3187
                ],
                [
                    8,
                    1,
                    "./static/experiments/de2/materials/stim_files/1.png",
                    "./static/experiments/de2/materials/stim_files/9.png",
                    null,
                    null,
                    null,
                    5150
                ],
                [
                    9,
                    1,
                    "./static/experiments/de2/materials/stim_files/16.png",
                    "./static/experiments/de2/materials/stim_files/8.png",
                    null,
                    null,
                    null,
                    3622
                ],
                [
                    10,
                    1,
                    "./static/experiments/de2/materials/stim_files/12.png",
                    "./static/experiments/de2/materials/stim_files/4.png",
                    null,
                    null,
                    null,
                    3882
                ],
                [
                    11,
                    1,
                    "./static/experiments/de2/materials/stim_files/15.png",
                    "./static/experiments/de2/materials/stim_files/7.png",
                    null,
                    null,
                    null,
                    3157
                ],
                [
                    12,
                    1,
                    "./static/experiments/de2/materials/stim_files/14.png",
                    "./static/experiments/de2/materials/stim_files/6.png",
                    null,
                    null,
                    null,
                    4210
                ],
                [
                    13,
                    1,
                    "./static/experiments/de2/materials/stim_files/14.png",
                    "./static/experiments/de2/materials/stim_files/6.png",
                    null,
                    null,
                    null,
                    3128
                ],
                [
                    14,
                    1,
                    "./static/experiments/de2/materials/stim_files/8.png",
                    "./static/experiments/de2/materials/stim_files/16.png",
                    null,
                    null,
                    null,
                    3408
                ],
                [
                    15,
                    1,
                    "./static/experiments/de2/materials/stim_files/13.png",
                    "./static/experiments/de2/materials/stim_files/5.png",
                    null,
                    null,
                    null,
                    3214
                ]
            ],
            "generalizationPhase": [
                [
                    "trial",
                    "block",
                    "s1",
                    "s2",
                    "connected",
                    "response",
                    "accuracy",
                    "rt",
                    "counter"
                ],
                [
                    0,
                    0,
                    "./static/experiments/de2/materials/stim_files/16.png",
                    "./static/experiments/de2/materials/stim_files/15.png",
                    2,
                    "no",
                    null,
                    7316,
                    0
                ],
                [
                    1,
                    0,
                    "./static/experiments/de2/materials/stim_files/2.png",
                    "./static/experiments/de2/materials/stim_files/4.png",
                    2,
                    "no",
                    null,
                    2091,
                    0
                ],
                [
                    2,
                    0,
                    "./static/experiments/de2/materials/stim_files/1.png",
                    "./static/experiments/de2/materials/stim_files/5.png",
                    2,
                    "yes",
                    null,
                    2180,
                    0
                ],
                [
                    3,
                    0,
                    "./static/experiments/de2/materials/stim_files/4.png",
                    "./static/experiments/de2/materials/stim_files/12.png",
                    2,
                    "yes",
                    null,
                    632,
                    0
                ],
                [
                    4,
                    0,
                    "./static/experiments/de2/materials/stim_files/9.png",
                    "./static/experiments/de2/materials/stim_files/12.png",
                    2,
                    "yes",
                    null,
                    2326,
                    0
                ],
                [
                    5,
                    0,
                    "./static/experiments/de2/materials/stim_files/10.png",
                    "./static/experiments/de2/materials/stim_files/2.png",
                    2,
                    "yes",
                    null,
                    1223,
                    0
                ],
                [
                    6,
                    0,
                    "./static/experiments/de2/materials/stim_files/2.png",
                    "./static/experiments/de2/materials/stim_files/14.png",
                    2,
                    "yes",
                    null,
                    1426,
                    0
                ],
                [
                    7,
                    0,
                    "./static/experiments/de2/materials/stim_files/2.png",
                    "./static/experiments/de2/materials/stim_files/12.png",
                    2,
                    "yes",
                    null,
                    593,
                    0
                ],
                [
                    8,
                    0,
                    "./static/experiments/de2/materials/stim_files/16.png",
                    "./static/experiments/de2/materials/stim_files/11.png",
                    2,
                    "no",
                    null,
                    1285,
                    0
                ],
                [
                    9,
                    0,
                    "./static/experiments/de2/materials/stim_files/1.png",
                    "./static/experiments/de2/materials/stim_files/7.png",
                    2,
                    "yes",
                    null,
                    1056,
                    0
                ],
                [
                    10,
                    0,
                    "./static/experiments/de2/materials/stim_files/16.png",
                    "./static/experiments/de2/materials/stim_files/2.png",
                    2,
                    "yes",
                    null,
                    771,
                    0
                ],
                [
                    11,
                    0,
                    "./static/experiments/de2/materials/stim_files/9.png",
                    "./static/experiments/de2/materials/stim_files/2.png",
                    2,
                    "yes",
                    null,
                    1220,
                    0
                ],
                [
                    12,
                    0,
                    "./static/experiments/de2/materials/stim_files/16.png",
                    "./static/experiments/de2/materials/stim_files/16.png",
                    2,
                    "no",
                    null,
                    664,
                    0
                ],
                [
                    13,
                    0,
                    "./static/experiments/de2/materials/stim_files/13.png",
                    "./static/experiments/de2/materials/stim_files/10.png",
                    2,
                    "no",
                    null,
                    710,
                    0
                ],
                [
                    14,
                    0,
                    "./static/experiments/de2/materials/stim_files/15.png",
                    "./static/experiments/de2/materials/stim_files/11.png",
                    2,
                    "no",
                    null,
                    1272,
                    0
                ],
                [
                    15,
                    0,
                    "./static/experiments/de2/materials/stim_files/5.png",
                    "./static/experiments/de2/materials/stim_files/14.png",
                    2,
                    "yes",
                    null,
                    683,
                    0
                ],
                [
                    16,
                    0,
                    "./static/experiments/de2/materials/stim_files/13.png",
                    "./static/experiments/de2/materials/stim_files/3.png",
                    2,
                    "yes",
                    null,
                    658,
                    0
                ],
                [
                    17,
                    0,
                    "./static/experiments/de2/materials/stim_files/16.png",
                    "./static/experiments/de2/materials/stim_files/1.png",
                    2,
                    "yes",
                    null,
                    523,
                    0
                ],
                [
                    18,
                    0,
                    "./static/experiments/de2/materials/stim_files/4.png",
                    "./static/experiments/de2/materials/stim_files/15.png",
                    2,
                    "yes",
                    null,
                    392,
                    0
                ],
                [
                    19,
                    0,
                    "./static/experiments/de2/materials/stim_files/15.png",
                    "./static/experiments/de2/materials/stim_files/6.png",
                    2,
                    "yes",
                    null,
                    461,
                    0
                ],
                [
                    20,
                    0,
                    "./static/experiments/de2/materials/stim_files/3.png",
                    "./static/experiments/de2/materials/stim_files/16.png",
                    2,
                    "yes",
                    null,
                    439,
                    0
                ],
                [
                    21,
                    0,
                    "./static/experiments/de2/materials/stim_files/3.png",
                    "./static/experiments/de2/materials/stim_files/14.png",
                    2,
                    "yes",
                    null,
                    438,
                    0
                ],
                [
                    22,
                    0,
                    "./static/experiments/de2/materials/stim_files/15.png",
                    "./static/experiments/de2/materials/stim_files/1.png",
                    2,
                    "yes",
                    null,
                    760,
                    0
                ],
                [
                    23,
                    0,
                    "./static/experiments/de2/materials/stim_files/9.png",
                    "./static/experiments/de2/materials/stim_files/2.png",
                    2,
                    "yes",
                    null,
                    356,
                    0
                ],
                [
                    24,
                    0,
                    "./static/experiments/de2/materials/stim_files/6.png",
                    "./static/experiments/de2/materials/stim_files/5.png",
                    2,
                    "no",
                    null,
                    399,
                    0
                ],
                [
                    25,
                    0,
                    "./static/experiments/de2/materials/stim_files/16.png",
                    "./static/experiments/de2/materials/stim_files/14.png",
                    2,
                    "no",
                    null,
                    606,
                    0
                ],
                [
                    26,
                    0,
                    "./static/experiments/de2/materials/stim_files/3.png",
                    "./static/experiments/de2/materials/stim_files/16.png",
                    2,
                    "yes",
                    null,
                    565,
                    0
                ],
                [
                    27,
                    0,
                    "./static/experiments/de2/materials/stim_files/7.png",
                    "./static/experiments/de2/materials/stim_files/13.png",
                    2,
                    "yes",
                    null,
                    464,
                    0
                ],
                [
                    28,
                    0,
                    "./static/experiments/de2/materials/stim_files/7.png",
                    "./static/experiments/de2/materials/stim_files/12.png",
                    2,
                    "yes",
                    null,
                    375,
                    0
                ],
                [
                    29,
                    0,
                    "./static/experiments/de2/materials/stim_files/6.png",
                    "./static/experiments/de2/materials/stim_files/6.png",
                    2,
                    "no",
                    null,
                    604,
                    0
                ],
                [
                    30,
                    0,
                    "./static/experiments/de2/materials/stim_files/16.png",
                    "./static/experiments/de2/materials/stim_files/1.png",
                    2,
                    "yes",
                    null,
                    464,
                    0
                ],
                [
                    31,
                    0,
                    "./static/experiments/de2/materials/stim_files/4.png",
                    "./static/experiments/de2/materials/stim_files/16.png",
                    2,
                    "yes",
                    null,
                    536,
                    0
                ]
            ]
        }
    }
}