{
    "id": "189",
    "condition": "4",
    "results": {
        "id": "189",
        "condition": "4",
        "results": {
            "trainingPhase": [
                [
                    "trial",
                    "block",
                    "s1",
                    "s2",
                    "connected",
                    "response",
                    "accuracy",
                    "rt"
                ],
                [
                    0,
                    0,
                    "./static/experiments/de2/materials/stim_files/11.png",
                    "./static/experiments/de2/materials/stim_files/11.png",
                    null,
                    null,
                    null,
                    5
                ],
                [
                    1,
                    0,
                    "./static/experiments/de2/materials/stim_files/1.png",
                    "./static/experiments/de2/materials/stim_files/1.png",
                    null,
                    null,
                    null,
                    10988
                ],
                [
                    2,
                    0,
                    "./static/experiments/de2/materials/stim_files/16.png",
                    "./static/experiments/de2/materials/stim_files/16.png",
                    null,
                    null,
                    null,
                    3704
                ],
                [
                    3,
                    0,
                    "./static/experiments/de2/materials/stim_files/2.png",
                    "./static/experiments/de2/materials/stim_files/2.png",
                    null,
                    null,
                    null,
                    5050
                ],
                [
                    4,
                    0,
                    "./static/experiments/de2/materials/stim_files/12.png",
                    "./static/experiments/de2/materials/stim_files/12.png",
                    null,
                    null,
                    null,
                    6482
                ],
                [
                    5,
                    0,
                    "./static/experiments/de2/materials/stim_files/3.png",
                    "./static/experiments/de2/materials/stim_files/3.png",
                    null,
                    null,
                    null,
                    3269
                ],
                [
                    6,
                    0,
                    "./static/experiments/de2/materials/stim_files/5.png",
                    "./static/experiments/de2/materials/stim_files/5.png",
                    null,
                    null,
                    null,
                    7557
                ],
                [
                    7,
                    0,
                    "./static/experiments/de2/materials/stim_files/9.png",
                    "./static/experiments/de2/materials/stim_files/9.png",
                    null,
                    null,
                    null,
                    3652
                ],
                [
                    8,
                    0,
                    "./static/experiments/de2/materials/stim_files/14.png",
                    "./static/experiments/de2/materials/stim_files/14.png",
                    null,
                    null,
                    null,
                    3566
                ],
                [
                    9,
                    0,
                    "./static/experiments/de2/materials/stim_files/7.png",
                    "./static/experiments/de2/materials/stim_files/7.png",
                    null,
                    null,
                    null,
                    1830
                ],
                [
                    10,
                    0,
                    "./static/experiments/de2/materials/stim_files/4.png",
                    "./static/experiments/de2/materials/stim_files/4.png",
                    null,
                    null,
                    null,
                    3312
                ],
                [
                    11,
                    0,
                    "./static/experiments/de2/materials/stim_files/6.png",
                    "./static/experiments/de2/materials/stim_files/6.png",
                    null,
                    null,
                    null,
                    2270
                ],
                [
                    12,
                    0,
                    "./static/experiments/de2/materials/stim_files/8.png",
                    "./static/experiments/de2/materials/stim_files/8.png",
                    null,
                    null,
                    null,
                    1806
                ],
                [
                    13,
                    0,
                    "./static/experiments/de2/materials/stim_files/13.png",
                    "./static/experiments/de2/materials/stim_files/13.png",
                    null,
                    null,
                    null,
                    2266
                ],
                [
                    14,
                    0,
                    "./static/experiments/de2/materials/stim_files/15.png",
                    "./static/experiments/de2/materials/stim_files/15.png",
                    null,
                    null,
                    null,
                    2209
                ],
                [
                    15,
                    0,
                    "./static/experiments/de2/materials/stim_files/10.png",
                    "./static/experiments/de2/materials/stim_files/10.png",
                    null,
                    null,
                    null,
                    2309
                ],
                [
                    0,
                    1,
                    "./static/experiments/de2/materials/stim_files/15.png",
                    "./static/experiments/de2/materials/stim_files/15.png",
                    null,
                    null,
                    null,
                    1995
                ],
                [
                    1,
                    1,
                    "./static/experiments/de2/materials/stim_files/7.png",
                    "./static/experiments/de2/materials/stim_files/7.png",
                    null,
                    null,
                    null,
                    3570
                ],
                [
                    2,
                    1,
                    "./static/experiments/de2/materials/stim_files/8.png",
                    "./static/experiments/de2/materials/stim_files/8.png",
                    null,
                    null,
                    null,
                    1841
                ],
                [
                    3,
                    1,
                    "./static/experiments/de2/materials/stim_files/10.png",
                    "./static/experiments/de2/materials/stim_files/10.png",
                    null,
                    null,
                    null,
                    2908
                ],
                [
                    4,
                    1,
                    "./static/experiments/de2/materials/stim_files/1.png",
                    "./static/experiments/de2/materials/stim_files/1.png",
                    null,
                    null,
                    null,
                    2563
                ],
                [
                    5,
                    1,
                    "./static/experiments/de2/materials/stim_files/5.png",
                    "./static/experiments/de2/materials/stim_files/5.png",
                    null,
                    null,
                    null,
                    2722
                ],
                [
                    6,
                    1,
                    "./static/experiments/de2/materials/stim_files/6.png",
                    "./static/experiments/de2/materials/stim_files/6.png",
                    null,
                    null,
                    null,
                    2085
                ],
                [
                    7,
                    1,
                    "./static/experiments/de2/materials/stim_files/13.png",
                    "./static/experiments/de2/materials/stim_files/13.png",
                    null,
                    null,
                    null,
                    2127
                ],
                [
                    8,
                    1,
                    "./static/experiments/de2/materials/stim_files/11.png",
                    "./static/experiments/de2/materials/stim_files/11.png",
                    null,
                    null,
                    null,
                    3079
                ],
                [
                    9,
                    1,
                    "./static/experiments/de2/materials/stim_files/16.png",
                    "./static/experiments/de2/materials/stim_files/16.png",
                    null,
                    null,
                    null,
                    2099
                ],
                [
                    10,
                    1,
                    "./static/experiments/de2/materials/stim_files/9.png",
                    "./static/experiments/de2/materials/stim_files/9.png",
                    null,
                    null,
                    null,
                    2154
                ],
                [
                    11,
                    1,
                    "./static/experiments/de2/materials/stim_files/2.png",
                    "./static/experiments/de2/materials/stim_files/2.png",
                    null,
                    null,
                    null,
                    2330
                ],
                [
                    12,
                    1,
                    "./static/experiments/de2/materials/stim_files/12.png",
                    "./static/experiments/de2/materials/stim_files/12.png",
                    null,
                    null,
                    null,
                    2427
                ],
                [
                    13,
                    1,
                    "./static/experiments/de2/materials/stim_files/4.png",
                    "./static/experiments/de2/materials/stim_files/4.png",
                    null,
                    null,
                    null,
                    2037
                ],
                [
                    14,
                    1,
                    "./static/experiments/de2/materials/stim_files/14.png",
                    "./static/experiments/de2/materials/stim_files/14.png",
                    null,
                    null,
                    null,
                    2802
                ],
                [
                    15,
                    1,
                    "./static/experiments/de2/materials/stim_files/3.png",
                    "./static/experiments/de2/materials/stim_files/3.png",
                    null,
                    null,
                    null,
                    1927
                ]
            ],
            "generalizationPhase": [
                [
                    "trial",
                    "block",
                    "s1",
                    "s2",
                    "connected",
                    "response",
                    "accuracy",
                    "rt",
                    "counter"
                ],
                [
                    0,
                    0,
                    "./static/experiments/de2/materials/stim_files/7.png",
                    "./static/experiments/de2/materials/stim_files/7.png",
                    2,
                    "yes",
                    null,
                    5672,
                    0
                ],
                [
                    1,
                    0,
                    "./static/experiments/de2/materials/stim_files/16.png",
                    "./static/experiments/de2/materials/stim_files/2.png",
                    2,
                    "no",
                    null,
                    1358,
                    0
                ],
                [
                    2,
                    0,
                    "./static/experiments/de2/materials/stim_files/2.png",
                    "./static/experiments/de2/materials/stim_files/12.png",
                    2,
                    "no",
                    null,
                    893,
                    0
                ],
                [
                    3,
                    0,
                    "./static/experiments/de2/materials/stim_files/3.png",
                    "./static/experiments/de2/materials/stim_files/16.png",
                    2,
                    "no",
                    null,
                    695,
                    0
                ],
                [
                    4,
                    0,
                    "./static/experiments/de2/materials/stim_files/15.png",
                    "./static/experiments/de2/materials/stim_files/4.png",
                    2,
                    "no",
                    null,
                    520,
                    0
                ],
                [
                    5,
                    0,
                    "./static/experiments/de2/materials/stim_files/4.png",
                    "./static/experiments/de2/materials/stim_files/12.png",
                    2,
                    "no",
                    null,
                    499,
                    0
                ],
                [
                    6,
                    0,
                    "./static/experiments/de2/materials/stim_files/9.png",
                    "./static/experiments/de2/materials/stim_files/2.png",
                    2,
                    "no",
                    null,
                    510,
                    0
                ],
                [
                    7,
                    0,
                    "./static/experiments/de2/materials/stim_files/4.png",
                    "./static/experiments/de2/materials/stim_files/9.png",
                    2,
                    "no",
                    null,
                    661,
                    0
                ],
                [
                    8,
                    0,
                    "./static/experiments/de2/materials/stim_files/1.png",
                    "./static/experiments/de2/materials/stim_files/1.png",
                    2,
                    "yes",
                    null,
                    901,
                    0
                ],
                [
                    9,
                    0,
                    "./static/experiments/de2/materials/stim_files/4.png",
                    "./static/experiments/de2/materials/stim_files/6.png",
                    2,
                    "no",
                    null,
                    819,
                    0
                ],
                [
                    10,
                    0,
                    "./static/experiments/de2/materials/stim_files/1.png",
                    "./static/experiments/de2/materials/stim_files/16.png",
                    2,
                    "no",
                    null,
                    631,
                    0
                ],
                [
                    11,
                    0,
                    "./static/experiments/de2/materials/stim_files/16.png",
                    "./static/experiments/de2/materials/stim_files/1.png",
                    2,
                    "no",
                    null,
                    659,
                    0
                ],
                [
                    12,
                    0,
                    "./static/experiments/de2/materials/stim_files/15.png",
                    "./static/experiments/de2/materials/stim_files/2.png",
                    2,
                    "no",
                    null,
                    474,
                    0
                ],
                [
                    13,
                    0,
                    "./static/experiments/de2/materials/stim_files/11.png",
                    "./static/experiments/de2/materials/stim_files/16.png",
                    2,
                    "no",
                    null,
                    656,
                    0
                ],
                [
                    14,
                    0,
                    "./static/experiments/de2/materials/stim_files/14.png",
                    "./static/experiments/de2/materials/stim_files/4.png",
                    2,
                    "no",
                    null,
                    502,
                    0
                ],
                [
                    15,
                    0,
                    "./static/experiments/de2/materials/stim_files/10.png",
                    "./static/experiments/de2/materials/stim_files/13.png",
                    2,
                    "no",
                    null,
                    768,
                    0
                ],
                [
                    16,
                    0,
                    "./static/experiments/de2/materials/stim_files/13.png",
                    "./static/experiments/de2/materials/stim_files/2.png",
                    2,
                    "no",
                    null,
                    487,
                    0
                ],
                [
                    17,
                    0,
                    "./static/experiments/de2/materials/stim_files/14.png",
                    "./static/experiments/de2/materials/stim_files/10.png",
                    2,
                    "no",
                    null,
                    579,
                    0
                ],
                [
                    18,
                    0,
                    "./static/experiments/de2/materials/stim_files/6.png",
                    "./static/experiments/de2/materials/stim_files/2.png",
                    2,
                    "no",
                    null,
                    794,
                    0
                ],
                [
                    19,
                    0,
                    "./static/experiments/de2/materials/stim_files/4.png",
                    "./static/experiments/de2/materials/stim_files/3.png",
                    2,
                    "no",
                    null,
                    1137,
                    0
                ],
                [
                    20,
                    0,
                    "./static/experiments/de2/materials/stim_files/6.png",
                    "./static/experiments/de2/materials/stim_files/8.png",
                    2,
                    "no",
                    null,
                    593,
                    0
                ],
                [
                    21,
                    0,
                    "./static/experiments/de2/materials/stim_files/14.png",
                    "./static/experiments/de2/materials/stim_files/2.png",
                    2,
                    "no",
                    null,
                    548,
                    0
                ],
                [
                    22,
                    0,
                    "./static/experiments/de2/materials/stim_files/1.png",
                    "./static/experiments/de2/materials/stim_files/8.png",
                    2,
                    "no",
                    null,
                    501,
                    0
                ],
                [
                    23,
                    0,
                    "./static/experiments/de2/materials/stim_files/3.png",
                    "./static/experiments/de2/materials/stim_files/12.png",
                    2,
                    "no",
                    null,
                    488,
                    0
                ],
                [
                    24,
                    0,
                    "./static/experiments/de2/materials/stim_files/11.png",
                    "./static/experiments/de2/materials/stim_files/5.png",
                    2,
                    "no",
                    null,
                    466,
                    0
                ],
                [
                    25,
                    0,
                    "./static/experiments/de2/materials/stim_files/15.png",
                    "./static/experiments/de2/materials/stim_files/1.png",
                    2,
                    "no",
                    null,
                    511,
                    0
                ],
                [
                    26,
                    0,
                    "./static/experiments/de2/materials/stim_files/6.png",
                    "./static/experiments/de2/materials/stim_files/9.png",
                    2,
                    "no",
                    null,
                    548,
                    0
                ],
                [
                    27,
                    0,
                    "./static/experiments/de2/materials/stim_files/13.png",
                    "./static/experiments/de2/materials/stim_files/1.png",
                    2,
                    "no",
                    null,
                    701,
                    0
                ],
                [
                    28,
                    0,
                    "./static/experiments/de2/materials/stim_files/15.png",
                    "./static/experiments/de2/materials/stim_files/6.png",
                    2,
                    "no",
                    null,
                    441,
                    0
                ],
                [
                    29,
                    0,
                    "./static/experiments/de2/materials/stim_files/2.png",
                    "./static/experiments/de2/materials/stim_files/3.png",
                    2,
                    "no",
                    null,
                    989,
                    0
                ],
                [
                    30,
                    0,
                    "./static/experiments/de2/materials/stim_files/10.png",
                    "./static/experiments/de2/materials/stim_files/16.png",
                    2,
                    "no",
                    null,
                    509,
                    0
                ],
                [
                    31,
                    0,
                    "./static/experiments/de2/materials/stim_files/6.png",
                    "./static/experiments/de2/materials/stim_files/14.png",
                    2,
                    "no",
                    null,
                    419,
                    0
                ]
            ]
        }
    }
}